setup.cfg
setup.py
djangorestframework_expander.egg-info/PKG-INFO
djangorestframework_expander.egg-info/SOURCES.txt
djangorestframework_expander.egg-info/dependency_links.txt
djangorestframework_expander.egg-info/requires.txt
djangorestframework_expander.egg-info/top_level.txt
expander/__init__.py
expander/parse_qs.py
expander/serializers.py