Metadata-Version: 1.1
Name: djangorestframework-expander
Version: 0.2.1
Summary: A serializer mixin for Django REST Framework to expand object representations inline
Home-page: https://github.com/silverlogic/djangorestframework-expander
Author: Ryan Pineo
Author-email: ryanpineo@gmail.com
License: MIT
Platform: UNKNOWN
Classifier: Environment :: Web Environment
Classifier: Framework :: Django
Classifier: Intended Audience :: Developers
Classifier: Programming Language :: Python
Classifier: Programming Language :: Python :: 2
Classifier: Programming Language :: Python :: 2.7
Classifier: Programming Language :: Python :: 3
Classifier: Programming Language :: Python :: 3.2
Classifier: Programming Language :: Python :: 3.3
Classifier: Programming Language :: Python :: 3.4
